amaxa/__init__.py
amaxa/__main__.py
amaxa/amaxa.py
amaxa/api.py
amaxa/constants.py
amaxa/jwt_auth.py
amaxa/loader/__init__.py
amaxa/loader/core.py
amaxa/loader/credentials.py
amaxa/loader/extract_operation.py
amaxa/loader/input_type.py
amaxa/loader/load_operation.py
amaxa/loader/schemas.py
amaxa/loader/state.py
amaxa/transforms.py
amaxa-0.9.8.dist-info/entry_points.txt
amaxa-0.9.8.dist-info/LICENSE
amaxa-0.9.8.dist-info/WHEEL
amaxa-0.9.8.dist-info/METADATA
amaxa-0.9.8.dist-info/RECORD
