Metadata-Version: 2.1
Name: amaxa
Version: 0.9.8
Summary: Load and extract data from multiple Salesforce objects in a single operation, preserving links and network structure.
Home-page: https://github.com/davidmreed/amaxa
License: BSD-3-Clause
Author: David Reed
Author-email: david@ktema.org
Requires-Python: >=3.7,<4.0
Classifier: Development Status :: 4 - Beta
Classifier: Environment :: Console
Classifier: License :: OSI Approved :: BSD License
Classifier: Operating System :: OS Independent
Classifier: Programming Language :: Python :: 3
Classifier: Programming Language :: Python :: 3.10
Classifier: Programming Language :: Python :: 3.7
Classifier: Programming Language :: Python :: 3.8
Classifier: Programming Language :: Python :: 3.9
Requires-Dist: Cerberus (>=1.3.4,<2.0.0)
Requires-Dist: PyJWT (>=2.1.0,<3.0.0)
Requires-Dist: PyYAML (>=5.4.1,<6.0.0)
Requires-Dist: cryptography (>=35.0.0,<36.0.0)
Requires-Dist: requests[security] (>=2.26.0,<3.0.0)
Requires-Dist: salesforce-bulk (>=2.2.0,<3.0.0)
Requires-Dist: simple-salesforce (>=1.11.4,<2.0.0)
Project-URL: Repository, https://github.com/davidmreed/amaxa
